jh2/__init__.py
jh2/_hazmat.pyi
jh2/config.py
jh2/connection.py
jh2/errors.py
jh2/events.py
jh2/exceptions.py
jh2/frame_buffer.py
jh2/settings.py
jh2/stream.py
jh2/utilities.py
jh2/windows.py
jh2/hpack/__init__.py
jh2/hpack/exceptions.py
jh2/hpack/hpack.py
jh2/hpack/huffman.py
jh2/hpack/huffman_constants.py
jh2/hpack/huffman_table.py
jh2/hpack/struct.py
jh2/hpack/table.py
jh2/hyperframe/__init__.py
jh2/hyperframe/exceptions.py
jh2/hyperframe/flags.py
jh2/hyperframe/frame.py
jh2/hyperframe/py.typed
jh2-5.0.9.dist-info/METADATA
jh2-5.0.9.dist-info/WHEEL
jh2-5.0.9.dist-info/licenses/LICENSE
jh2-5.0.9.dist-info/RECORD
