Metadata-Version: 2.4
Name: jh2
Version: 5.0.9
Summary: HTTP/2 State-Machine based protocol implementation
Project-URL: Changelog, https://github.com/jawah/h2/blob/main/CHANGELOG.rst
Project-URL: Code, https://github.com/jawah/h2
Project-URL: Issue tracker, https://github.com/jawah/h2/issues
Author-email: Cory Benfield <cory@lukasa.co.uk>
Maintainer-email: "Ahmed R. TAHRI" <ahmed.tahri@cloudnursery.dev>
License-Expression: MIT
License-File: LICENSE
Keywords: h2,hpack,http2
Classifier: Development Status :: 5 - Production/Stable
Classifier: Environment :: Web Environment
Classifier: Intended Audience :: Developers
Classifier: License :: OSI Approved :: Apache Software License
Classifier: Natural Language :: English
Classifier: Operating System :: OS Independent
Classifier: Programming Language :: Python
Classifier: Programming Language :: Python :: 3
Classifier: Programming Language :: Python :: 3 :: Only
Classifier: Programming Language :: Python :: 3.7
Classifier: Programming Language :: Python :: 3.8
Classifier: Programming Language :: Python :: 3.9
Classifier: Programming Language :: Python :: 3.10
Classifier: Programming Language :: Python :: 3.11
Classifier: Programming Language :: Python :: 3.12
Classifier: Programming Language :: Python :: 3.13
Classifier: Programming Language :: Python :: Implementation :: CPython
Classifier: Programming Language :: Python :: Implementation :: PyPy
Classifier: Topic :: Internet :: WWW/HTTP
Classifier: Topic :: Software Development :: Libraries
Requires-Python: >=3.7
